setup.py
disuniv/Binomialdistribution.py
disuniv/Gaussiandistribution.py
disuniv/Generaldistribution.py
disuniv/__init__.py
disuniv.egg-info/PKG-INFO
disuniv.egg-info/SOURCES.txt
disuniv.egg-info/dependency_links.txt
disuniv.egg-info/not-zip-safe
disuniv.egg-info/top_level.txt