Metadata-Version: 1.0
Name: disuniv
Version: 0.1
Summary: Gaussian distributions and Binomial Distributions
Home-page: UNKNOWN
Author: Rushikesh Dixit
Author-email: r29dixit@gmail.com
License: UNKNOWN
Platform: UNKNOWN
